{
    "totalrecords": 5,
    "labels": [
        {
            "scope": "problem-type",
            "name": "Classification"
        },
        {
            "scope": "problem-type",
            "name": "Clustering"
        },
        {
            "scope": "problem-type",
            "name": "Dimensionality Reduction"
        },
        {
            "scope": "problem-type",
            "name": "Natural Language Processing"
        },
        {
            "scope": "problem-type",
            "name": "Text Classification"
        },
        {

        },
        {

        },
        {

        }
    ]
}
